personaflow/__init__.py
personaflow-0.1.3.dist-info/licenses/LICENSE
personaflow-0.1.3.dist-info/METADATA
personaflow-0.1.3.dist-info/WHEEL
personaflow-0.1.3.dist-info/top_level.txt
personaflow-0.1.3.dist-info/RECORD
