Metadata-Version: 2.4
Name: personaflow
Version: 0.1.3
Summary: A lightweight Python library for managing dynamic multi-persona interactions with LLMs.
Author-email: "Zhiyong (Justin) He" <justin.he814@gmail.com>
License: MIT
Project-URL: Homepage, https://github.com/Ate329/PersonaFlow
Project-URL: Repository, https://github.com/Ate329/PersonaFlow
Project-URL: Issues, https://github.com/Ate329/PersonaFlow/issues
Classifier: Programming Language :: Python :: 3
Classifier: License :: OSI Approved :: MIT License
Classifier: Operating System :: OS Independent
Classifier: Development Status :: 3 - Alpha
Classifier: Intended Audience :: Developers
Classifier: Topic :: Software Development :: Libraries :: Python Modules
Classifier: Topic :: Scientific/Engineering :: Artificial Intelligence
Requires-Python: >=3.12
License-File: LICENSE
Requires-Dist: torch
Requires-Dist: transformers>=4.45.0
Requires-Dist: accelerate
Requires-Dist: typing-extensions
Dynamic: license-file
